[
  {
    "title": "Football Word Search Book",
    "emoji": "⚽",
    "description": "Word searches for football fans.",
    "image": "/puzzle-playhouse/images/football-book.jpg",
    "link": "https://amzn.to/41ZXleZ",
    "newRelease": false
  },
  {
    "title": "Dino Word Search",
    "emoji": "🦖",
    "description": "Word searches for the prehistoric fans.",
    "image": "/puzzle-playhouse/images/Dino_word_search.jpg",
    "link": "https://amzn.to/41pxT2r",
    "newRelease": false
  },
  {
    "title": "Ice Hockey Crosswords",
    "emoji": "🏒",
    "description": "Ice Hockey crosswords fun for all ages.",
    "image": "/puzzle-playhouse/images/Ice_Hocky_X.jpg",
    "link": "https://amzn.to/48zXd9L",
    "newRelease": false
  },
  {
    "title": "Word Scramble",
    "emoji": "🔠",
    "description": "Fun and Educational Word Jumble Game.",
    "image": "/puzzle-playhouse/images/Word_Scramble.jpg",
    "link": "https://amzn.to/4t4HSq4",
    "newRelease": false
  },
  {
    "title": "Block Craft",
    "emoji": "🧱",
    "description": "Word Searches and Crosswords, Fun for Creative Kids.",
    "image": "/puzzle-playhouse/images/BlockCraft.png",
    "link": "https://amzn.to/4sSvmKa",
    "newRelease": true
  },
  {
    "title": "Football Crossword",
    "emoji": "🏟️",
    "description": "Crosswords for Football Fans.",
    "image": "/puzzle-playhouse/images/Football_Crossword.png",
    "link": "https://amzn.to/4sqoX7P",
    "newRelease": true
  }
]
